{
  "name": "Virginia Stevenson",
  "age": 50,
  "address": {
    "street": "Soak Path",
    "city": "Mikihaj",
    "state": "MA",
    "zip": "61189"
  },
  "contact": {
    "phone": "(641) 800-5107",
    "servicePhone": "800298821"
  },
  "birthday": "1971-11-12T08:06:52.408Z",
  "ip": "242.231.122.70",
  "foo": "bar",
  "profile": {
    "about": "Tuc gizulej cod debti fenizi tob notohosig tidi miv ultel nawvuk emoel. Fajedus ofa fijre sed lu eb kesod duhajges pe hu sibobeiga ke. Itvemfun cos ocson hi hupe ojbohu gaiw re dujemo ido hokamune egufiztej. Jedtiutu aspam dib tanda uz sunodcev na se deccufcej waphej rubin toreav len fahkebom. Aju legirvuh sisedsa fovenmu ofane fetesho ehi teedkar codpemugi uja re piltit itvuf.",
    "bio": "Ri ah jeb ot bonu pa lo ha agu pum oguwuki ku cu tedvon ov huluidu bawga ru. Pega abuji darles ro johavvev nar duwseok lur ciser hukaha ozo wuwot mopomcun napede nocbube odse. Ukitav le lasja opotuf nofe ril hes kaf bos varim bo cik. Ihize launodog wuw huz ajujib kit codha cuhe rawu matowu suzagi vi. Jacgoag adbeac koktuhri tepo ohdi hudas ugsiwviv buab kak giwu wiwhava evfod kangecru. Waksa ciutjet nuvlu owtiop parotaj casume wojoc pisu matiav nawnogmij wil kunfij cicloznu riji al wokopne. Zobriva du tatpilusa hol rubufi on gigkol akidojo enguvil ka uv hin berer soj vawipop ripak nolufe gabi."
  },
  "apiKey": "37180e6920fe10eaa3366f911548734eb8b80d61c725c0f1a91f7cf09ce15232",
  "currency": {
    "code": "FKP",
    "name": "Falkland Islands (Malvinas) Pound"
  }
}