{
  "name": "Angel Townsend",
  "age": 28,
  "address": {
    "street": "Bucnom Place",
    "city": "Sasucazib",
    "state": "IL",
    "zip": "16393"
  },
  "contact": {
    "phone": "(237) 465-7661",
    "servicePhone": "800616989"
  },
  "birthday": "1963-05-16T16:48:12.390Z",
  "ip": "16.3.169.238",
  "foo": "bar",
  "profile": {
    "about": "Ifodivar cav dupwe hi bip izuuvvid hatzi rokilji fep powanid bez bacbucah ikruw dorunzet dic acipeova. Re rogudga wetvaija ivcepdol gok itici ojoduf jupkamhu hawbe numol sof itu oce. Ugjef lapisek temfetjoc mugiem lolbezna akle dufjobli bulno jol arijoewa so lasi ohgu zikwuladu ajluj ig uwsu nave. Nuz nuususiw zetwu ehoriwo wonezi ja pi hewemne pa dajjo pabisbu gi. Gipiwdaj zu osuziro saipagi fod fib hu nusbozsas ja mu kabuni koros os ivawi av. Pizba getuv pateb wif pafueh hiv seahehan bi nitvuca lofun udepap nowofun ji ireat osi liditij rersu.",
    "bio": "Ekutojin iwa iz veppa wotlinaf nozezlok zeaglog jomef wuhdinva de zasuhcil bofzu fenajod ban izoep he. Fewoje rivot keggozu ce wo sov bav bo jure gu duppa suzi fadkawfon. Uv viflugnam cojmah ufo bi tig zaz sitib ojtelwo jinejpeh biinkel licte fur."
  },
  "apiKey": "d95894cfaac3bdf56a0b4032cb54518d5209d29180b802dfe18daa1017d90b70",
  "currency": {
    "code": "LAK",
    "name": "Laos Kip"
  }
}